{
    "data": {
        "order_id": "7476967516541534883",
        "uid": 194897199,
        "code": "CSI666",
        "name": "螺丝钉指数基金组合",
        "ttype": "plan",
        "status": "success",
        "action": "022",
        "amount": 244.46,
        "status_desc": "交易成功",
        "action_desc": "买入",
        "created_at": 1574125874519,
        "final_confirm_date": 1574179200000,
        "total_confirm_amount": 244.45999999999998,
        "total_fee": 0.31,
        "title": "螺丝钉指数基金组合",
        "bank_name": "工商银行(0930)",
        "value_desc": "244.46元",
        "sub_order_list": [
            {
                "action_text": "成分基金交易信息",
                "action": "022",
                "orders": [
                    {
                        "plan_code": "CSI666",
                        "plan_name": "螺丝钉指数基金组合",
                        "fd_code": "519671",
                        "fd_name": "银河沪深300价值指数",
                        "title": "银河沪深300价值指数",
                        "action_desc": "买入",
                        "status_desc": "交易成功",
                        "type": "plan",
                        "action": "022",
                        "status": "success",
                        "ts": 1574092800000,
                        "confirm_ts": 1574179200000,
                        "amount": 47.01,
                        "volume": 0,
                        "confirm_amount": 47.01,
                        "confirm_volume": 32.4,
                        "fee": 0.06,
                        "value_desc": "47.01元",
                        "value_text": "下单金额",
                        "confirm_value_text": "确认份额",
                        "confirm_value_desc": "32.40份",
                        "bank_name": "工商银行(0930)",
                        "order_id": "165835970956378112"
                    },
                    {
                        "plan_code": "CSI666",
                        "plan_name": "螺丝钉指数基金组合",
                        "fd_code": "090010",
                        "fd_name": "大成中证红利指数A",
                        "title": "大成中证红利指数A",
                        "action_desc": "买入",
                        "status_desc": "交易成功",
                        "type": "plan",
                        "action": "022",
                        "status": "success",
                        "ts": 1574092800000,
                        "confirm_ts": 1574179200000,
                        "amount": 46.37,
                        "volume": 0,
                        "confirm_amount": 46.37,
                        "confirm_volume": 28.53,
                        "fee": 0.06,
                        "value_desc": "46.37元",
                        "value_text": "下单金额",
                        "confirm_value_text": "确认份额",
                        "confirm_value_desc": "28.53份",
                        "bank_name": "工商银行(0930)",
                        "order_id": "165835970981543936"
                    },
                    {
                        "plan_code": "CSI666",
                        "plan_name": "螺丝钉指数基金组合",
                        "fd_code": "000968",
                        "fd_name": "广发中证养老",
                        "title": "广发中证养老",
                        "action_desc": "买入",
                        "status_desc": "交易成功",
                        "type": "plan",
                        "action": "022",
                        "status": "success",
                        "ts": 1574092800000,
                        "confirm_ts": 1574179200000,
                        "amount": 33.39,
                        "volume": 0,
                        "confirm_amount": 33.39,
                        "confirm_volume": 34,
                        "fee": 0.04,
                        "value_desc": "33.39元",
                        "value_text": "下单金额",
                        "confirm_value_text": "确认份额",
                        "confirm_value_desc": "34.00份",
                        "bank_name": "工商银行(0930)",
                        "order_id": "165835971010904064"
                    },
                    {
                        "plan_code": "CSI666",
                        "plan_name": "螺丝钉指数基金组合",
                        "fd_code": "530015",
                        "fd_name": "建信深证基本面60ETF联接A",
                        "title": "建信深证基本面60ETF联接A",
                        "action_desc": "买入",
                        "status_desc": "交易成功",
                        "type": "plan",
                        "action": "022",
                        "status": "success",
                        "ts": 1574092800000,
                        "confirm_ts": 1574179200000,
                        "amount": 38.01,
                        "volume": 0,
                        "confirm_amount": 38.01,
                        "confirm_volume": 17.5,
                        "fee": 0.06,
                        "value_desc": "38.01元",
                        "value_text": "下单金额",
                        "confirm_value_text": "确认份额",
                        "confirm_value_desc": "17.50份",
                        "bank_name": "工商银行(0930)",
                        "order_id": "165835971036069888"
                    },
                    {
                        "plan_code": "CSI666",
                        "plan_name": "螺丝钉指数基金组合",
                        "fd_code": "070023",
                        "fd_name": "嘉实深证基本面120联接",
                        "title": "嘉实深证基本面120联接",
                        "action_desc": "买入",
                        "status_desc": "交易成功",
                        "type": "plan",
                        "action": "022",
                        "status": "success",
                        "ts": 1574092800000,
                        "confirm_ts": 1574179200000,
                        "amount": 35.72,
                        "volume": 0,
                        "confirm_amount": 35.72,
                        "confirm_volume": 19.11,
                        "fee": 0.04,
                        "value_desc": "35.72元",
                        "value_text": "下单金额",
                        "confirm_value_text": "确认份额",
                        "confirm_value_desc": "19.11份",
                        "bank_name": "工商银行(0930)",
                        "order_id": "165835971052847104"
                    },
                    {
                        "plan_code": "CSI666",
                        "plan_name": "螺丝钉指数基金组合",
                        "fd_code": "003318",
                        "fd_name": "景顺长城中证500低波动",
                        "title": "景顺长城中证500低波动",
                        "action_desc": "买入",
                        "status_desc": "交易成功",
                        "type": "plan",
                        "action": "022",
                        "status": "success",
                        "ts": 1574092800000,
                        "confirm_ts": 1574179200000,
                        "amount": 43.96,
                        "volume": 0,
                        "confirm_amount": 43.96,
                        "confirm_volume": 47.57,
                        "fee": 0.05,
                        "value_desc": "43.96元",
                        "value_text": "下单金额",
                        "confirm_value_text": "确认份额",
                        "confirm_value_desc": "47.57份",
                        "bank_name": "工商银行(0930)",
                        "order_id": "165835971078012928"
                    }
                ]
            }
        ],
        "convert": false
    },
    "result_code": 0
}