{
    "data": {
        "order_id": "7801614001802213240",
        "uid": 576923716,
        "code": "CSI666",
        "name": "螺丝钉指数基金组合",
        "ttype": "plan",
        "status": "success",
        "action": "022",
        "amount": 122.29,
        "status_desc": "交易成功",
        "action_desc": "买入",
        "created_at": 1575335276912,
        "final_confirm_date": 1575388800000,
        "total_confirm_amount": 122.28999999999999,
        "total_fee": 0.16,
        "title": "螺丝钉指数基金组合",
        "bank_name": "建设银行(2247)",
        "value_desc": "122.29元",
        "sub_order_list": [
            {
                "action_text": "成分基金交易信息",
                "action": "022",
                "orders": [
                    {
                        "plan_code": "CSI666",
                        "plan_name": "螺丝钉指数基金组合",
                        "fd_code": "519671",
                        "fd_name": "银河沪深300价值指数",
                        "title": "银河沪深300价值指数",
                        "action_desc": "买入",
                        "status_desc": "交易成功",
                        "type": "plan",
                        "action": "022",
                        "status": "success",
                        "ts": 1575302400000,
                        "confirm_ts": 1575388800000,
                        "amount": 23.01,
                        "volume": 0,
                        "confirm_amount": 23.01,
                        "confirm_volume": 16.06,
                        "fee": 0.03,
                        "value_desc": "23.01元",
                        "value_text": "下单金额",
                        "confirm_value_text": "确认份额",
                        "confirm_value_desc": "16.06份",
                        "bank_name": "建设银行(2247)",
                        "order_id": "170908572284502016"
                    },
                    {
                        "plan_code": "CSI666",
                        "plan_name": "螺丝钉指数基金组合",
                        "fd_code": "090010",
                        "fd_name": "大成中证红利指数A",
                        "title": "大成中证红利指数A",
                        "action_desc": "买入",
                        "status_desc": "交易成功",
                        "type": "plan",
                        "action": "022",
                        "status": "success",
                        "ts": 1575302400000,
                        "confirm_ts": 1575388800000,
                        "amount": 23.08,
                        "volume": 0,
                        "confirm_amount": 23.08,
                        "confirm_volume": 14.26,
                        "fee": 0.03,
                        "value_desc": "23.08元",
                        "value_text": "下单金额",
                        "confirm_value_text": "确认份额",
                        "confirm_value_desc": "14.26份",
                        "bank_name": "建设银行(2247)",
                        "order_id": "170908572309667840"
                    },
                    {
                        "plan_code": "CSI666",
                        "plan_name": "螺丝钉指数基金组合",
                        "fd_code": "530015",
                        "fd_name": "建信深证基本面60ETF联接A",
                        "title": "建信深证基本面60ETF联接A",
                        "action_desc": "买入",
                        "status_desc": "交易成功",
                        "type": "plan",
                        "action": "022",
                        "status": "success",
                        "ts": 1575302400000,
                        "confirm_ts": 1575388800000,
                        "amount": 19.04,
                        "volume": 0,
                        "confirm_amount": 19.04,
                        "confirm_volume": 8.82,
                        "fee": 0.03,
                        "value_desc": "19.04元",
                        "value_text": "下单金额",
                        "confirm_value_text": "确认份额",
                        "confirm_value_desc": "8.82份",
                        "bank_name": "建设银行(2247)",
                        "order_id": "170908572330639360"
                    },
                    {
                        "plan_code": "CSI666",
                        "plan_name": "螺丝钉指数基金组合",
                        "fd_code": "003318",
                        "fd_name": "景顺长城中证500低波动",
                        "title": "景顺长城中证500低波动",
                        "action_desc": "买入",
                        "status_desc": "交易成功",
                        "type": "plan",
                        "action": "022",
                        "status": "success",
                        "ts": 1575302400000,
                        "confirm_ts": 1575388800000,
                        "amount": 21.72,
                        "volume": 0,
                        "confirm_amount": 21.72,
                        "confirm_volume": 23.68,
                        "fee": 0.03,
                        "value_desc": "21.72元",
                        "value_text": "下单金额",
                        "confirm_value_text": "确认份额",
                        "confirm_value_desc": "23.68份",
                        "bank_name": "建设银行(2247)",
                        "order_id": "170908572351610880"
                    },
                    {
                        "plan_code": "CSI666",
                        "plan_name": "螺丝钉指数基金组合",
                        "fd_code": "000968",
                        "fd_name": "广发中证养老",
                        "title": "广发中证养老",
                        "action_desc": "买入",
                        "status_desc": "交易成功",
                        "type": "plan",
                        "action": "022",
                        "status": "success",
                        "ts": 1575302400000,
                        "confirm_ts": 1575388800000,
                        "amount": 17.45,
                        "volume": 0,
                        "confirm_amount": 17.45,
                        "confirm_volume": 18.54,
                        "fee": 0.02,
                        "value_desc": "17.45元",
                        "value_text": "下单金额",
                        "confirm_value_text": "确认份额",
                        "confirm_value_desc": "18.54份",
                        "bank_name": "建设银行(2247)",
                        "order_id": "170908572376776704"
                    },
                    {
                        "plan_code": "CSI666",
                        "plan_name": "螺丝钉指数基金组合",
                        "fd_code": "070023",
                        "fd_name": "嘉实深证基本面120联接",
                        "title": "嘉实深证基本面120联接",
                        "action_desc": "买入",
                        "status_desc": "交易成功",
                        "type": "plan",
                        "action": "022",
                        "status": "success",
                        "ts": 1575302400000,
                        "confirm_ts": 1575388800000,
                        "amount": 17.99,
                        "volume": 0,
                        "confirm_amount": 17.99,
                        "confirm_volume": 9.68,
                        "fee": 0.02,
                        "value_desc": "17.99元",
                        "value_text": "下单金额",
                        "confirm_value_text": "确认份额",
                        "confirm_value_desc": "9.68份",
                        "bank_name": "建设银行(2247)",
                        "order_id": "170908572397748224"
                    }
                ]
            }
        ],
        "convert": false
    },
    "result_code": 0
}