{
    "data": {
        "order_id": "5529655427872126604",
        "uid": 203274561,
        "code": "CSI666",
        "name": "螺丝钉指数基金组合",
        "ttype": "plan",
        "status": "success",
        "action": "022",
        "amount": 659.55,
        "status_desc": "交易成功",
        "action_desc": "买入",
        "created_at": 1566871571698,
        "final_confirm_date": 1566921600000,
        "total_confirm_amount": 659.55,
        "total_fee": 0.79,
        "title": "螺丝钉指数基金组合",
        "bank_name": "招商银行(6292)",
        "value_desc": "659.55元",
        "sub_order_list": [
            {
                "action_text": "成分基金交易信息",
                "action": "022",
                "orders": [
                    {
                        "plan_code": "CSI666",
                        "plan_name": "螺丝钉指数基金组合",
                        "fd_code": "519671",
                        "fd_name": "银河沪深300价值指数",
                        "title": "银河沪深300价值指数",
                        "action_desc": "买入",
                        "status_desc": "交易成功",
                        "type": "plan",
                        "action": "022",
                        "status": "success",
                        "ts": 1566835200000,
                        "confirm_ts": 1566921600000,
                        "amount": 125.25,
                        "volume": 0,
                        "confirm_amount": 125.25,
                        "confirm_volume": 76.28,
                        "fee": 0.15,
                        "value_desc": "125.25元",
                        "value_text": "下单金额",
                        "confirm_value_text": "确认份额",
                        "confirm_value_desc": "76.28份",
                        "bank_name": "招商银行(6292)",
                        "order_id": "135409219567001600"
                    },
                    {
                        "plan_code": "CSI666",
                        "plan_name": "螺丝钉指数基金组合",
                        "fd_code": "090010",
                        "fd_name": "大成中证红利指数A",
                        "title": "大成中证红利指数A",
                        "action_desc": "买入",
                        "status_desc": "交易成功",
                        "type": "plan",
                        "action": "022",
                        "status": "success",
                        "ts": 1566835200000,
                        "confirm_ts": 1566921600000,
                        "amount": 120.57,
                        "volume": 0,
                        "confirm_amount": 120.57,
                        "confirm_volume": 74.34,
                        "fee": 0.14,
                        "value_desc": "120.57元",
                        "value_text": "下单金额",
                        "confirm_value_text": "确认份额",
                        "confirm_value_desc": "74.34份",
                        "bank_name": "招商银行(6292)",
                        "order_id": "135409219587973120"
                    },
                    {
                        "plan_code": "CSI666",
                        "plan_name": "螺丝钉指数基金组合",
                        "fd_code": "501021",
                        "fd_name": "华宝香港中小",
                        "title": "华宝香港中小",
                        "action_desc": "买入",
                        "status_desc": "交易成功",
                        "type": "plan",
                        "action": "022",
                        "status": "success",
                        "ts": 1566835200000,
                        "confirm_ts": 1566921600000,
                        "amount": 98.08,
                        "volume": 0,
                        "confirm_amount": 98.08,
                        "confirm_volume": 73.44,
                        "fee": 0.1,
                        "value_desc": "98.08元",
                        "value_text": "下单金额",
                        "confirm_value_text": "确认份额",
                        "confirm_value_desc": "73.44份",
                        "bank_name": "招商银行(6292)",
                        "order_id": "135409219604750336"
                    },
                    {
                        "plan_code": "CSI666",
                        "plan_name": "螺丝钉指数基金组合",
                        "fd_code": "530015",
                        "fd_name": "建信深证基本面60ETF联接A",
                        "title": "建信深证基本面60ETF联接A",
                        "action_desc": "买入",
                        "status_desc": "交易成功",
                        "type": "plan",
                        "action": "022",
                        "status": "success",
                        "ts": 1566835200000,
                        "confirm_ts": 1566921600000,
                        "amount": 102.63,
                        "volume": 0,
                        "confirm_amount": 102.63,
                        "confirm_volume": 49.19,
                        "fee": 0.15,
                        "value_desc": "102.63元",
                        "value_text": "下单金额",
                        "confirm_value_text": "确认份额",
                        "confirm_value_desc": "49.19份",
                        "bank_name": "招商银行(6292)",
                        "order_id": "135409219625721856"
                    },
                    {
                        "plan_code": "CSI666",
                        "plan_name": "螺丝钉指数基金组合",
                        "fd_code": "070023",
                        "fd_name": "嘉实深证基本面120联接",
                        "title": "嘉实深证基本面120联接",
                        "action_desc": "买入",
                        "status_desc": "交易成功",
                        "type": "plan",
                        "action": "022",
                        "status": "success",
                        "ts": 1566835200000,
                        "confirm_ts": 1566921600000,
                        "amount": 100.98,
                        "volume": 0,
                        "confirm_amount": 100.98,
                        "confirm_volume": 56.25,
                        "fee": 0.12,
                        "value_desc": "100.98元",
                        "value_text": "下单金额",
                        "confirm_value_text": "确认份额",
                        "confirm_value_desc": "56.25份",
                        "bank_name": "招商银行(6292)",
                        "order_id": "135409219646693376"
                    },
                    {
                        "plan_code": "CSI666",
                        "plan_name": "螺丝钉指数基金组合",
                        "fd_code": "003318",
                        "fd_name": "景顺长城中证500低波动",
                        "title": "景顺长城中证500低波动",
                        "action_desc": "买入",
                        "status_desc": "交易成功",
                        "type": "plan",
                        "action": "022",
                        "status": "success",
                        "ts": 1566835200000,
                        "confirm_ts": 1566921600000,
                        "amount": 112.04,
                        "volume": 0,
                        "confirm_amount": 112.04,
                        "confirm_volume": 120.13,
                        "fee": 0.13,
                        "value_desc": "112.04元",
                        "value_text": "下单金额",
                        "confirm_value_text": "确认份额",
                        "confirm_value_desc": "120.13份",
                        "bank_name": "招商银行(6292)",
                        "order_id": "135409219667664896"
                    }
                ]
            }
        ],
        "convert": false
    },
    "result_code": 0
}