{
    "data": {
        "order_id": "871185187803806491",
        "uid": 203274561,
        "code": "003474",
        "name": "南方天天利货币B",
        "ttype": "plan",
        "status": "success",
        "action": "036",
        "percent": 0,
        "volume": 10000.79,
        "target_code": "CSI1019",
        "target_name": "钉钉宝365天组合",
        "status_desc": "交易成功",
        "action_desc": "转换",
        "created_at": 1581053417709,
        "final_confirm_date": 1581264000000,
        "total_fee": 0,
        "title": "南方天天利货币B->钉钉宝365天组合",
        "sub_order_list": [
            {
                "action_text": "成分基金转换信息",
                "action": "036",
                "orders": [
                    {
                        "fd_code": "003474",
                        "fd_name": "南方天天利货币B",
                        "target_plan_code": "CSI1019",
                        "target_plan_name": "钉钉宝365天组合",
                        "target_fd_code": "002147",
                        "target_fd_name": "长安鑫益增强混合C",
                        "title": "南方天天利货币B->长安鑫益增强混合C",
                        "action_desc": "转换",
                        "status_desc": "交易成功",
                        "type": "plan",
                        "action": "036",
                        "status": "success",
                        "ts": 1581004800000,
                        "confirm_ts": 1581264000000,
                        "amount": 0,
                        "volume": 4144.33,
                        "confirm_amount": 4144.33,
                        "confirm_volume": 3419.98,
                        "fee": 0,
                        "value_desc": "4144.33份",
                        "value_text": "下单份额",
                        "confirm_value_text": "确认份额",
                        "confirm_value_desc": "3419.98份",
                        "bank_name": "招商银行(6292)",
                        "order_id": "194892193072852992"
                    },
                    {
                        "fd_code": "003474",
                        "fd_name": "南方天天利货币B",
                        "target_plan_code": "CSI1019",
                        "target_plan_name": "钉钉宝365天组合",
                        "target_fd_code": "001338",
                        "target_fd_name": "安信稳健增值混合C",
                        "title": "南方天天利货币B->安信稳健增值混合C",
                        "action_desc": "转换",
                        "status_desc": "交易成功",
                        "type": "plan",
                        "action": "036",
                        "status": "success",
                        "ts": 1581004800000,
                        "confirm_ts": 1581264000000,
                        "amount": 0,
                        "volume": 1024.08,
                        "confirm_amount": 1024.08,
                        "confirm_volume": 762.36,
                        "fee": 0,
                        "value_desc": "1024.08份",
                        "value_text": "下单份额",
                        "confirm_value_text": "确认份额",
                        "confirm_value_desc": "762.36份",
                        "bank_name": "招商银行(6292)",
                        "order_id": "194892193152544768"
                    },
                    {
                        "fd_code": "003474",
                        "fd_name": "南方天天利货币B",
                        "target_plan_code": "CSI1019",
                        "target_plan_name": "钉钉宝365天组合",
                        "target_fd_code": "485011",
                        "target_fd_name": "工银双利债券B",
                        "title": "南方天天利货币B->工银双利债券B",
                        "action_desc": "转换",
                        "status_desc": "交易成功",
                        "type": "plan",
                        "action": "036",
                        "status": "success",
                        "ts": 1581004800000,
                        "confirm_ts": 1581264000000,
                        "amount": 0,
                        "volume": 988.08,
                        "confirm_amount": 988.08,
                        "confirm_volume": 633.79,
                        "fee": 0,
                        "value_desc": "988.08份",
                        "value_text": "下单份额",
                        "confirm_value_text": "确认份额",
                        "confirm_value_desc": "633.79份",
                        "bank_name": "招商银行(6292)",
                        "order_id": "194892193244819456"
                    },
                    {
                        "fd_code": "003474",
                        "fd_name": "南方天天利货币B",
                        "target_plan_code": "CSI1019",
                        "target_plan_name": "钉钉宝365天组合",
                        "target_fd_code": "006060",
                        "target_fd_name": "鹏扬泓利债券C",
                        "title": "南方天天利货币B->鹏扬泓利债券C",
                        "action_desc": "转换",
                        "status_desc": "交易成功",
                        "type": "plan",
                        "action": "036",
                        "status": "success",
                        "ts": 1581004800000,
                        "confirm_ts": 1581264000000,
                        "amount": 0,
                        "volume": 1967.16,
                        "confirm_amount": 1967.16,
                        "confirm_volume": 1809.71,
                        "fee": 0,
                        "value_desc": "1967.16份",
                        "value_text": "下单份额",
                        "confirm_value_text": "确认份额",
                        "confirm_value_desc": "1809.71份",
                        "bank_name": "招商银行(6292)",
                        "order_id": "194892193345482752"
                    },
                    {
                        "fd_code": "003474",
                        "fd_name": "南方天天利货币B",
                        "target_plan_code": "CSI1019",
                        "target_plan_name": "钉钉宝365天组合",
                        "target_fd_code": "007749",
                        "target_fd_name": "民生加银鹏程混合C",
                        "title": "南方天天利货币B->民生加银鹏程混合C",
                        "action_desc": "转换",
                        "status_desc": "交易成功",
                        "type": "plan",
                        "action": "036",
                        "status": "success",
                        "ts": 1581004800000,
                        "confirm_ts": 1581264000000,
                        "amount": 0,
                        "volume": 1877.14,
                        "confirm_amount": 1877.14,
                        "confirm_volume": 1756.8,
                        "fee": 0,
                        "value_desc": "1877.14份",
                        "value_text": "下单份额",
                        "confirm_value_text": "确认份额",
                        "confirm_value_desc": "1756.80份",
                        "bank_name": "招商银行(6292)",
                        "order_id": "194892193416785920"
                    }
                ]
            }
        ],
        "convert": true
    },
    "result_code": 0
}