{
    "orderProdType": "PO",
    "orderId": "PO202002259D0NKWP608TS",
    "payStatus": "0",
    "uiPayStatusName": "处理中",
    "confirmStatus": "P2",
    "uiConfirmStatusName": "确认成功",
    "capitalAccountId": "CA942R8128PFE7",
    "uiAmount": 200000,
    "hasDetail": true,
    "po": {
        "poCode": "ZH013136",
        "poName": "我要稳稳的幸福"
    },
    "umaId": null,
    "umaName": null,
    "orderCode": "P03",
    "uiOrderCodeName": "卖出至银行卡",
    "orderStatus": "SUCCESS",
    "uiOrderStatusName": "成功",
    "capitalAccountName": "我要稳稳的幸福",
    "totalFee": 453.7,
    "totalReceiveAmount": 199489.45,
    "capitalTips": "由于基金卖出成交后才披露成交净值（未知价法），因此到账金额与下单金额可能有所差别，您可以在交易进度明细中通过实际卖出份额、成交净值和手续费进行核算",
    "transferIntoDate": 1582819200000,
    "orderConfirmDate": 1582646400000,
    "receiveAcctName": "建设银行(尾号2247)",
    "acceptTime": 1582612421000,
    "compositionOrders": [
        {
            "orderId": "2020022501736670",
            "payStatus": "0",
            "cancelable": false,
            "acceptTime": 1582612421000,
            "transferIntoDate": 1582732800000,
            "nav": 1.0309,
            "fee": 0,
            "uiAmount": 19887.68,
            "uiShare": 19291.57,
            "confirmStatus": "2",
            "orderStatus": "SUCCESS",
            "uiOrderStatusName": "成功",
            "uiConfirmStatusName": "成功",
            "tradeByShare": true,
            "orderCode": "024",
            "uiOrderCodeName": "赎回",
            "orderConfirmDate": 1582646400000,
            "fund": {
                "fundCode": "006793",
                "fundName": "交银稳鑫短债债券A"
            },
            "uiOrderDesc": "已于2020年2月26日确认完成，已于2020年2月27日资金到账"
        },
        {
            "orderId": "2020022501736672",
            "payStatus": "0",
            "cancelable": false,
            "acceptTime": 1582612421000,
            "transferIntoDate": 1582732800000,
            "nav": 1.161,
            "fee": 37.66,
            "uiAmount": 37621.2,
            "uiShare": 32436.57,
            "confirmStatus": "2",
            "orderStatus": "SUCCESS",
            "uiOrderStatusName": "成功",
            "uiConfirmStatusName": "成功",
            "tradeByShare": true,
            "orderCode": "024",
            "uiOrderCodeName": "赎回",
            "orderConfirmDate": 1582646400000,
            "fund": {
                "fundCode": "164902",
                "fundName": "交银信用添利债券(LOF)"
            },
            "uiOrderDesc": "已于2020年2月26日确认完成，已于2020年2月27日资金到账"
        },
        {
            "orderId": "2020022501736674",
            "payStatus": "0",
            "cancelable": false,
            "acceptTime": 1582612421000,
            "transferIntoDate": 1582819200000,
            "nav": 1.74,
            "fee": 24.65,
            "uiAmount": 4905.92,
            "uiShare": 2833.66,
            "confirmStatus": "2",
            "orderStatus": "SUCCESS",
            "uiOrderStatusName": "成功",
            "uiConfirmStatusName": "成功",
            "tradeByShare": true,
            "orderCode": "024",
            "uiOrderCodeName": "赎回",
            "orderConfirmDate": 1582646400000,
            "fund": {
                "fundCode": "519700",
                "fundName": "交银主题优选"
            },
            "uiOrderDesc": "已于2020年2月26日确认完成，已于2020年2月28日资金到账"
        },
        {
            "orderId": "2020022501736676",
            "payStatus": "0",
            "cancelable": false,
            "acceptTime": 1582612421000,
            "transferIntoDate": 1582732800000,
            "nav": 1.09,
            "fee": 38.51,
            "uiAmount": 38471.69,
            "uiShare": 35330.46,
            "confirmStatus": "2",
            "orderStatus": "SUCCESS",
            "uiOrderStatusName": "成功",
            "uiConfirmStatusName": "成功",
            "tradeByShare": true,
            "orderCode": "024",
            "uiOrderCodeName": "赎回",
            "orderConfirmDate": 1582646400000,
            "fund": {
                "fundCode": "519718",
                "fundName": "交银纯债A/B"
            },
            "uiOrderDesc": "已于2020年2月26日确认完成，已于2020年2月27日资金到账"
        },
        {
            "orderId": "2020022501736678",
            "payStatus": "0",
            "cancelable": false,
            "acceptTime": 1582612421000,
            "transferIntoDate": 1582732800000,
            "nav": 1.083,
            "fee": 35.48,
            "uiAmount": 35440.67,
            "uiShare": 32757.29,
            "confirmStatus": "2",
            "orderStatus": "SUCCESS",
            "uiOrderStatusName": "成功",
            "uiConfirmStatusName": "成功",
            "tradeByShare": true,
            "orderCode": "024",
            "uiOrderCodeName": "赎回",
            "orderConfirmDate": 1582646400000,
            "fund": {
                "fundCode": "519723",
                "fundName": "交银双轮动A/B"
            },
            "uiOrderDesc": "已于2020年2月26日确认完成，已于2020年2月27日资金到账"
        },
        {
            "orderId": "2020022501736680",
            "payStatus": "0",
            "cancelable": false,
            "acceptTime": 1582612421000,
            "transferIntoDate": 1582819200000,
            "nav": 1.175,
            "fee": 99.35,
            "uiAmount": 19770.11,
            "uiShare": 16910.18,
            "confirmStatus": "2",
            "orderStatus": "SUCCESS",
            "uiOrderStatusName": "成功",
            "uiConfirmStatusName": "成功",
            "tradeByShare": true,
            "orderCode": "024",
            "uiOrderCodeName": "赎回",
            "orderConfirmDate": 1582646400000,
            "fund": {
                "fundCode": "519738",
                "fundName": "交银周期回报灵活配置混合A"
            },
            "uiOrderDesc": "已于2020年2月26日确认完成，已于2020年2月28日资金到账"
        },
        {
            "orderId": "2020022501736682",
            "payStatus": "0",
            "cancelable": false,
            "acceptTime": 1582612421000,
            "transferIntoDate": 1582819200000,
            "nav": 1.277,
            "fee": 93.1,
            "uiAmount": 18527.72,
            "uiShare": 14581.69,
            "confirmStatus": "2",
            "orderStatus": "SUCCESS",
            "uiOrderStatusName": "成功",
            "uiConfirmStatusName": "成功",
            "tradeByShare": true,
            "orderCode": "024",
            "uiOrderCodeName": "赎回",
            "orderConfirmDate": 1582646400000,
            "fund": {
                "fundCode": "519752",
                "fundName": "交银新回报灵活配置混合A"
            },
            "uiOrderDesc": "已于2020年2月26日确认完成，已于2020年2月28日资金到账"
        },
        {
            "orderId": "2020022501736684",
            "payStatus": "0",
            "cancelable": false,
            "acceptTime": 1582612421000,
            "transferIntoDate": 1582819200000,
            "nav": 1.329,
            "fee": 124.95,
            "uiAmount": 24864.46,
            "uiShare": 18803.17,
            "confirmStatus": "2",
            "orderStatus": "SUCCESS",
            "uiOrderStatusName": "成功",
            "uiConfirmStatusName": "成功",
            "tradeByShare": true,
            "orderCode": "024",
            "uiOrderCodeName": "赎回",
            "orderConfirmDate": 1582646400000,
            "fund": {
                "fundCode": "519755",
                "fundName": "交银多策略回报灵活配置混合A"
            },
            "uiOrderDesc": "已于2020年2月26日确认完成，已于2020年2月28日资金到账"
        }
    ],
    "cancelable": false
}