[
    {
        "id": 1,
        "date": "2017-02-08",
        "code": "nan",
        "name": " ",
        "dealType": "卖出",
        "nav_unit": 0.0,
        "nav_acc": 0.0,
        "volume": 0,
        "dealMoney": 10000.0,
        "fee": 0.0,
        "occurMoney": 10000.0,
        "account": "华泰证券",
        "category1": "无",
        "category2": "无",
        "category3": "无",
        "categoryId": 1,
        "note": "银行返回码[ ]返回信息[0000 交易成功]|转账成功"
    },
    {
        "id": 2,
        "date": "2017-02-14",
        "code": "nan",
        "name": " ",
        "dealType": "卖出",
        "nav_unit": 0.0,
        "nav_acc": 0.0,
        "volume": 0,
        "dealMoney": 200.0,
        "fee": 0.0,
        "occurMoney": 200.0,
        "account": "华泰证券",
        "category1": "无",
        "category2": "无",
        "category3": "无",
        "categoryId": 1,
        "note": "银行返回码[ ]返回信息[0000 交易成功]|转账成功"
    },
    {
        "id": 3,
        "date": "2017-02-16",
        "code": "nan",
        "name": " ",
        "dealType": "卖出",
        "nav_unit": 0.0,
        "nav_acc": 0.0,
        "volume": 0,
        "dealMoney": 4000.0,
        "fee": 0.0,
        "occurMoney": 4000.0,
        "account": "华泰证券",
        "category1": "无",
        "category2": "无",
        "category3": "无",
        "categoryId": 1,
        "note": "银行返回码[ ]返回信息[0000 交易成功]|转账成功"
    },
    {
        "id": 4,
        "date": "2017-03-21",
        "code": "nan",
        "name": " ",
        "dealType": "卖出",
        "nav_unit": 0.0,
        "nav_acc": 0.0,
        "volume": 0,
        "dealMoney": 2.38,
        "fee": 0.0,
        "occurMoney": 2.38,
        "account": "华泰证券",
        "category1": "无",
        "category2": "无",
        "category3": "无",
        "categoryId": 1,
        "note": " 利息归本: 归本利息为 2.38"
    },
    {
        "id": 5,
        "date": "2017-04-25",
        "code": "nan",
        "name": " ",
        "dealType": "卖出",
        "nav_unit": 0.0,
        "nav_acc": 0.0,
        "volume": 0,
        "dealMoney": 11880.0,
        "fee": 0.0,
        "occurMoney": 11880.0,
        "account": "华泰证券",
        "category1": "无",
        "category2": "无",
        "category3": "无",
        "categoryId": 1,
        "note": "银行返回码[ ]返回信息[0000 交易成功]|转账成功"
    },
    {
        "id": 6,
        "date": "2017-05-05",
        "code": "nan",
        "name": " ",
        "dealType": "卖出",
        "nav_unit": 0.0,
        "nav_acc": 0.0,
        "volume": 0,
        "dealMoney": 10000.0,
        "fee": 0.0,
        "occurMoney": 10000.0,
        "account": "华泰证券",
        "category1": "无",
        "category2": "无",
        "category3": "无",
        "categoryId": 1,
        "note": "银行返回码[ ]返回信息[0000 交易成功]|转账成功correct_balance=0"
    },
    {
        "id": 7,
        "date": "2017-05-23",
        "code": "nan",
        "name": " ",
        "dealType": "卖出",
        "nav_unit": 0.0,
        "nav_acc": 0.0,
        "volume": 0,
        "dealMoney": 5737.0,
        "fee": 0.0,
        "occurMoney": 5737.0,
        "account": "华泰证券",
        "category1": "无",
        "category2": "无",
        "category3": "无",
        "categoryId": 1,
        "note": "银行返回码[ ]返回信息[0000 交易成功]|转账成功correct_balance=5737"
    },
    {
        "id": 8,
        "date": "2017-05-23",
        "code": "nan",
        "name": " ",
        "dealType": "卖出",
        "nav_unit": 0.0,
        "nav_acc": 0.0,
        "volume": 0,
        "dealMoney": 7542.0,
        "fee": 0.0,
        "occurMoney": 7542.0,
        "account": "华泰证券",
        "category1": "无",
        "category2": "无",
        "category3": "无",
        "categoryId": 1,
        "note": "银行返回码[ ]返回信息[0000 交易成功]|转账成功correct_balance=7542"
    },
    {
        "id": 9,
        "date": "2017-05-24",
        "code": "nan",
        "name": " ",
        "dealType": "卖出",
        "nav_unit": 0.0,
        "nav_acc": 0.0,
        "volume": 0,
        "dealMoney": 12000.0,
        "fee": 0.0,
        "occurMoney": 12000.0,
        "account": "华泰证券",
        "category1": "无",
        "category2": "无",
        "category3": "无",
        "categoryId": 1,
        "note": "银行返回码[ ]返回信息[0000 交易成功]|转账成功correct_balance=12000"
    },
    {
        "id": 10,
        "date": "2017-06-21",
        "code": "nan",
        "name": " ",
        "dealType": "卖出",
        "nav_unit": 0.0,
        "nav_acc": 0.0,
        "volume": 0,
        "dealMoney": 1.18,
        "fee": 0.0,
        "occurMoney": 1.18,
        "account": "华泰证券",
        "category1": "无",
        "category2": "无",
        "category3": "无",
        "categoryId": 1,
        "note": " 利息归本: 归本利息为 1.18correct_balance=0"
    },
    {
        "id": 11,
        "date": "2017-08-04",
        "code": "nan",
        "name": " ",
        "dealType": "卖出",
        "nav_unit": 0.0,
        "nav_acc": 0.0,
        "volume": 0,
        "dealMoney": 25000.0,
        "fee": 0.0,
        "occurMoney": 25000.0,
        "account": "华泰证券",
        "category1": "无",
        "category2": "无",
        "category3": "无",
        "categoryId": 1,
        "note": "银行返回码[ ]返回信息[0000 交易成功]|转账成功correct_balance=0"
    },
    {
        "id": 12,
        "date": "2017-11-24",
        "code": "nan",
        "name": " ",
        "dealType": "卖出",
        "nav_unit": 0.0,
        "nav_acc": 0.0,
        "volume": 0,
        "dealMoney": 7600.0,
        "fee": 0.0,
        "occurMoney": 7600.0,
        "account": "华泰证券",
        "category1": "无",
        "category2": "无",
        "category3": "无",
        "categoryId": 1,
        "note": "银行返回码[ ]返回信息[0000 交易成功]|转账成功correct_balance=0"
    },
    {
        "id": 13,
        "date": "2017-12-05",
        "code": "nan",
        "name": " ",
        "dealType": "卖出",
        "nav_unit": 0.0,
        "nav_acc": 0.0,
        "volume": 0,
        "dealMoney": 4000.0,
        "fee": 0.0,
        "occurMoney": 4000.0,
        "account": "华泰证券",
        "category1": "无",
        "category2": "无",
        "category3": "无",
        "categoryId": 1,
        "note": "银行返回码[ ]返回信息[0000 交易成功]|转账成功correct_balance=0"
    },
    {
        "id": 14,
        "date": "2017-12-26",
        "code": "nan",
        "name": " ",
        "dealType": "卖出",
        "nav_unit": 0.0,
        "nav_acc": 0.0,
        "volume": 0,
        "dealMoney": 500.0,
        "fee": 0.0,
        "occurMoney": 500.0,
        "account": "华泰证券",
        "category1": "无",
        "category2": "无",
        "category3": "无",
        "categoryId": 1,
        "note": "银行返回码[ ]返回信息[0000 交易成功]|转账成功correct_balance=0"
    },
    {
        "id": 15,
        "date": "2017-12-29",
        "code": "004749",
        "name": " ",
        "dealType": "卖出",
        "nav_unit": 0.0,
        "nav_acc": 0.0,
        "volume": 0,
        "dealMoney": 1000.0,
        "fee": 0.0,
        "occurMoney": 1000.0,
        "account": "华泰证券",
        "category1": "无",
        "category2": "无",
        "category3": "无",
        "categoryId": 1,
        "note": "124增加金额 基金代码：004749,发生份额：1000"
    },
    {
        "id": 16,
        "date": "2018-01-31",
        "code": "nan",
        "name": " ",
        "dealType": "卖出",
        "nav_unit": 0.0,
        "nav_acc": 0.0,
        "volume": 0,
        "dealMoney": 110000.0,
        "fee": 0.0,
        "occurMoney": 110000.0,
        "account": "华泰证券",
        "category1": "无",
        "category2": "无",
        "category3": "无",
        "categoryId": 1,
        "note": "银行返回码[ ]返回信息[0000 交易成功]|转账成功correct_balance=0"
    },
    {
        "id": 17,
        "date": "2018-02-06",
        "code": "nan",
        "name": " ",
        "dealType": "卖出",
        "nav_unit": 0.0,
        "nav_acc": 0.0,
        "volume": 0,
        "dealMoney": 2000.0,
        "fee": 0.0,
        "occurMoney": 2000.0,
        "account": "华泰证券",
        "category1": "无",
        "category2": "无",
        "category3": "无",
        "categoryId": 1,
        "note": "银行返回码[ ]返回信息[0000 交易成功]|转账成功correct_balance=0"
    },
    {
        "id": 18,
        "date": "2018-02-09",
        "code": "nan",
        "name": " ",
        "dealType": "卖出",
        "nav_unit": 0.0,
        "nav_acc": 0.0,
        "volume": 0,
        "dealMoney": 8000.0,
        "fee": 0.0,
        "occurMoney": 8000.0,
        "account": "华泰证券",
        "category1": "无",
        "category2": "无",
        "category3": "无",
        "categoryId": 1,
        "note": "银行返回码[ ]返回信息[0000 交易成功]|转账成功correct_balance=0"
    },
    {
        "id": 19,
        "date": "2018-03-21",
        "code": "nan",
        "name": " ",
        "dealType": "卖出",
        "nav_unit": 0.0,
        "nav_acc": 0.0,
        "volume": 0,
        "dealMoney": 0.17,
        "fee": 0.0,
        "occurMoney": 0.17,
        "account": "华泰证券",
        "category1": "无",
        "category2": "无",
        "category3": "无",
        "categoryId": 1,
        "note": " 利息归本: 归本利息为 0.17correct_balance=0"
    },
    {
        "id": 20,
        "date": "2018-04-19",
        "code": "nan",
        "name": " ",
        "dealType": "卖出",
        "nav_unit": 0.0,
        "nav_acc": 0.0,
        "volume": 0,
        "dealMoney": 1177.0,
        "fee": 0.0,
        "occurMoney": 1177.0,
        "account": "华泰证券",
        "category1": "无",
        "category2": "无",
        "category3": "无",
        "categoryId": 1,
        "note": "银行返回码[ ]返回信息[0000 交易成功]|转账成功correct_balance=1177"
    },
    {
        "id": 21,
        "date": "2018-04-25",
        "code": "nan",
        "name": " ",
        "dealType": "卖出",
        "nav_unit": 0.0,
        "nav_acc": 0.0,
        "volume": 0,
        "dealMoney": 150.0,
        "fee": 0.0,
        "occurMoney": 150.0,
        "account": "华泰证券",
        "category1": "无",
        "category2": "无",
        "category3": "无",
        "categoryId": 1,
        "note": "银行返回码[ ]返回信息[0000 交易成功]|转账成功correct_balance=0"
    },
    {
        "id": 22,
        "date": "2018-04-27",
        "code": "nan",
        "name": " ",
        "dealType": "卖出",
        "nav_unit": 0.0,
        "nav_acc": 0.0,
        "volume": 0,
        "dealMoney": 3690.0,
        "fee": 0.0,
        "occurMoney": 3690.0,
        "account": "华泰证券",
        "category1": "无",
        "category2": "无",
        "category3": "无",
        "categoryId": 1,
        "note": "银行返回码[ ]返回信息[0000 交易成功]|转账成功correct_balance=3690"
    },
    {
        "id": 23,
        "date": "2018-05-09",
        "code": "nan",
        "name": " ",
        "dealType": "卖出",
        "nav_unit": 0.0,
        "nav_acc": 0.0,
        "volume": 0,
        "dealMoney": 3000.0,
        "fee": 0.0,
        "occurMoney": 3000.0,
        "account": "华泰证券",
        "category1": "无",
        "category2": "无",
        "category3": "无",
        "categoryId": 1,
        "note": "银行返回码[ ]返回信息[0000 交易成功]|转账成功correct_balance=0"
    },
    {
        "id": 24,
        "date": "2018-05-15",
        "code": "nan",
        "name": " ",
        "dealType": "卖出",
        "nav_unit": 0.0,
        "nav_acc": 0.0,
        "volume": 0,
        "dealMoney": 30872.0,
        "fee": 0.0,
        "occurMoney": 30872.0,
        "account": "华泰证券",
        "category1": "无",
        "category2": "无",
        "category3": "无",
        "categoryId": 1,
        "note": "银行返回码[ ]返回信息[0000 交易成功]|转账成功correct_balance=30872"
    },
    {
        "id": 25,
        "date": "2018-06-14",
        "code": "nan",
        "name": " ",
        "dealType": "卖出",
        "nav_unit": 0.0,
        "nav_acc": 0.0,
        "volume": 0,
        "dealMoney": 6400.0,
        "fee": 0.0,
        "occurMoney": 6400.0,
        "account": "华泰证券",
        "category1": "无",
        "category2": "无",
        "category3": "无",
        "categoryId": 1,
        "note": "银行返回码[ ]返回信息[0000 交易成功]|转账成功 转账账号:6225881012906292 correct_balance=6400"
    },
    {
        "id": 26,
        "date": "2018-06-19",
        "code": "nan",
        "name": " ",
        "dealType": "卖出",
        "nav_unit": 0.0,
        "nav_acc": 0.0,
        "volume": 0,
        "dealMoney": 12800.0,
        "fee": 0.0,
        "occurMoney": 12800.0,
        "account": "华泰证券",
        "category1": "无",
        "category2": "无",
        "category3": "无",
        "categoryId": 1,
        "note": "银行返回码[ ]返回信息[0000 交易成功]|转账成功 转账账号:6225881012906292 correct_balance=12800"
    },
    {
        "id": 27,
        "date": "2018-06-19",
        "code": "nan",
        "name": " ",
        "dealType": "卖出",
        "nav_unit": 0.0,
        "nav_acc": 0.0,
        "volume": 0,
        "dealMoney": 2000.0,
        "fee": 0.0,
        "occurMoney": 2000.0,
        "account": "华泰证券",
        "category1": "无",
        "category2": "无",
        "category3": "无",
        "categoryId": 1,
        "note": "银行返回码[ ]返回信息[0000 交易成功]|转账成功 转账账号:6225881012906292 correct_balance=0"
    },
    {
        "id": 28,
        "date": "2018-06-21",
        "code": "nan",
        "name": " ",
        "dealType": "卖出",
        "nav_unit": 0.0,
        "nav_acc": 0.0,
        "volume": 0,
        "dealMoney": 0.06,
        "fee": 0.0,
        "occurMoney": 0.06,
        "account": "华泰证券",
        "category1": "无",
        "category2": "无",
        "category3": "无",
        "categoryId": 1,
        "note": " 利息归本: 归本利息为 0.06correct_balance=0"
    },
    {
        "id": 29,
        "date": "2018-06-29",
        "code": "nan",
        "name": " ",
        "dealType": "卖出",
        "nav_unit": 0.0,
        "nav_acc": 0.0,
        "volume": 0,
        "dealMoney": 12800.0,
        "fee": 0.0,
        "occurMoney": 12800.0,
        "account": "华泰证券",
        "category1": "无",
        "category2": "无",
        "category3": "无",
        "categoryId": 1,
        "note": "银行返回码[ ]返回信息[0000 交易成功]|转账成功 转账账号:6225881012906292 correct_balance=12800"
    },
    {
        "id": 30,
        "date": "2018-07-03",
        "code": "nan",
        "name": " ",
        "dealType": "卖出",
        "nav_unit": 0.0,
        "nav_acc": 0.0,
        "volume": 0,
        "dealMoney": 32000.0,
        "fee": 0.0,
        "occurMoney": 32000.0,
        "account": "华泰证券",
        "category1": "无",
        "category2": "无",
        "category3": "无",
        "categoryId": 1,
        "note": "银行返回码[ ]返回信息[0000 交易成功]|转账成功 转账账号:6225881012906292 correct_balance=32000"
    },
    {
        "id": 31,
        "date": "2018-07-06",
        "code": "nan",
        "name": " ",
        "dealType": "卖出",
        "nav_unit": 0.0,
        "nav_acc": 0.0,
        "volume": 0,
        "dealMoney": 102400.0,
        "fee": 0.0,
        "occurMoney": 102400.0,
        "account": "华泰证券",
        "category1": "无",
        "category2": "无",
        "category3": "无",
        "categoryId": 1,
        "note": "银行返回码[ ]返回信息[0000 交易成功]|转账成功 转账账号:6225881012906292 correct_balance=102400"
    },
    {
        "id": 32,
        "date": "2018-07-17",
        "code": "nan",
        "name": " ",
        "dealType": "卖出",
        "nav_unit": 0.0,
        "nav_acc": 0.0,
        "volume": 0,
        "dealMoney": 36.5,
        "fee": 0.0,
        "occurMoney": 36.5,
        "account": "华泰证券",
        "category1": "无",
        "category2": "无",
        "category3": "无",
        "categoryId": 1,
        "note": "银行返回码[ ]返回信息[0000 交易成功]|转账成功 转账账号:6225881012906292 correct_balance=36.5"
    },
    {
        "id": 33,
        "date": "2018-07-20",
        "code": "nan",
        "name": " ",
        "dealType": "卖出",
        "nav_unit": 0.0,
        "nav_acc": 0.0,
        "volume": 0,
        "dealMoney": 19200.0,
        "fee": 0.0,
        "occurMoney": 19200.0,
        "account": "华泰证券",
        "category1": "无",
        "category2": "无",
        "category3": "无",
        "categoryId": 1,
        "note": "银行返回码[ ]返回信息[0000 交易成功]|转账成功 转账账号:6225881012906292 correct_balance=19200"
    },
    {
        "id": 34,
        "date": "2018-08-06",
        "code": "nan",
        "name": " ",
        "dealType": "卖出",
        "nav_unit": 0.0,
        "nav_acc": 0.0,
        "volume": 0,
        "dealMoney": 3200.0,
        "fee": 0.0,
        "occurMoney": 3200.0,
        "account": "华泰证券",
        "category1": "无",
        "category2": "无",
        "category3": "无",
        "categoryId": 1,
        "note": "银行返回码[ ]返回信息[0000 交易成功]|转账成功 转账账号:6225881012906292 correct_balance=0"
    },
    {
        "id": 35,
        "date": "2018-08-06",
        "code": "nan",
        "name": " ",
        "dealType": "卖出",
        "nav_unit": 0.0,
        "nav_acc": 0.0,
        "volume": 0,
        "dealMoney": 800.0,
        "fee": 0.0,
        "occurMoney": 800.0,
        "account": "华泰证券",
        "category1": "无",
        "category2": "无",
        "category3": "无",
        "categoryId": 1,
        "note": "银行返回码[ ]返回信息[0000 交易成功]|转账成功 转账账号:6225881012906292 correct_balance=0"
    },
    {
        "id": 36,
        "date": "2018-09-03",
        "code": "nan",
        "name": " ",
        "dealType": "卖出",
        "nav_unit": 0.0,
        "nav_acc": 0.0,
        "volume": 0,
        "dealMoney": 12000.0,
        "fee": 0.0,
        "occurMoney": 12000.0,
        "account": "华泰证券",
        "category1": "无",
        "category2": "无",
        "category3": "无",
        "categoryId": 1,
        "note": "银行返回码[ ]返回信息[0000 交易成功]|转账成功 转账账号:6225881012906292 correct_balance=0"
    },
    {
        "id": 37,
        "date": "2018-09-05",
        "code": "nan",
        "name": " ",
        "dealType": "卖出",
        "nav_unit": 0.0,
        "nav_acc": 0.0,
        "volume": 0,
        "dealMoney": 165005.16,
        "fee": 0.0,
        "occurMoney": 165005.16,
        "account": "华泰证券",
        "category1": "无",
        "category2": "无",
        "category3": "无",
        "categoryId": 1,
        "note": "银行返回码[ ]返回信息[0000 交易成功]|转账成功 转账账号:6225881012906292 correct_balance=165005.16"
    },
    {
        "id": 38,
        "date": "2018-09-11",
        "code": "nan",
        "name": " ",
        "dealType": "卖出",
        "nav_unit": 0.0,
        "nav_acc": 0.0,
        "volume": 0,
        "dealMoney": 3210.0,
        "fee": 0.0,
        "occurMoney": 3210.0,
        "account": "华泰证券",
        "category1": "无",
        "category2": "无",
        "category3": "无",
        "categoryId": 1,
        "note": "银行返回码[ ]返回信息[0000 交易成功]|转账成功 转账账号:6225881012906292 correct_balance=0"
    },
    {
        "id": 39,
        "date": "2018-09-14",
        "code": "nan",
        "name": " ",
        "dealType": "卖出",
        "nav_unit": 0.0,
        "nav_acc": 0.0,
        "volume": 0,
        "dealMoney": 10000.0,
        "fee": 0.0,
        "occurMoney": 10000.0,
        "account": "华泰证券",
        "category1": "无",
        "category2": "无",
        "category3": "无",
        "categoryId": 1,
        "note": "银行返回码[ ]返回信息[0000 交易成功]|转账成功 转账账号:6225881012906292 correct_balance=0"
    },
    {
        "id": 40,
        "date": "2018-09-21",
        "code": "nan",
        "name": " ",
        "dealType": "卖出",
        "nav_unit": 0.0,
        "nav_acc": 0.0,
        "volume": 0,
        "dealMoney": 3000.0,
        "fee": 0.0,
        "occurMoney": 3000.0,
        "account": "华泰证券",
        "category1": "无",
        "category2": "无",
        "category3": "无",
        "categoryId": 1,
        "note": "银行返回码[ ]返回信息[0000 交易成功]|转账成功 转账账号:6225881012906292 correct_balance=0"
    },
    {
        "id": 41,
        "date": "2018-09-21",
        "code": "nan",
        "name": " ",
        "dealType": "卖出",
        "nav_unit": 0.0,
        "nav_acc": 0.0,
        "volume": 0,
        "dealMoney": 1.6,
        "fee": 0.0,
        "occurMoney": 1.6,
        "account": "华泰证券",
        "category1": "无",
        "category2": "无",
        "category3": "无",
        "categoryId": 1,
        "note": " 利息归本: 归本利息为 1.6correct_balance=0"
    },
    {
        "id": 42,
        "date": "2018-10-11",
        "code": "nan",
        "name": " ",
        "dealType": "卖出",
        "nav_unit": 0.0,
        "nav_acc": 0.0,
        "volume": 0,
        "dealMoney": 6400.0,
        "fee": 0.0,
        "occurMoney": 6400.0,
        "account": "华泰证券",
        "category1": "无",
        "category2": "无",
        "category3": "无",
        "categoryId": 1,
        "note": "银行返回码[ ]返回信息[0000 交易成功]|转账成功 转账账号:6225881012906292 correct_balance=0"
    },
    {
        "id": 43,
        "date": "2018-10-15",
        "code": "nan",
        "name": " ",
        "dealType": "卖出",
        "nav_unit": 0.0,
        "nav_acc": 0.0,
        "volume": 0,
        "dealMoney": 6400.0,
        "fee": 0.0,
        "occurMoney": 6400.0,
        "account": "华泰证券",
        "category1": "无",
        "category2": "无",
        "category3": "无",
        "categoryId": 1,
        "note": "银行返回码[ ]返回信息[0000 交易成功]|转账成功 转账账号:6225881012906292 correct_balance=0"
    },
    {
        "id": 44,
        "date": "2019-02-19",
        "code": "nan",
        "name": " ",
        "dealType": "卖出",
        "nav_unit": 0.0,
        "nav_acc": 0.0,
        "volume": 0,
        "dealMoney": 10000.0,
        "fee": 0.0,
        "occurMoney": 10000.0,
        "account": "华泰证券",
        "category1": "无",
        "category2": "无",
        "category3": "无",
        "categoryId": 1,
        "note": "银行返回码[ ]返回信息[0000 交易成功]|转账成功 转账账号:6225881012906292 correct_balance=0"
    },
    {
        "id": 45,
        "date": "2019-02-20",
        "code": "003474",
        "name": " ",
        "dealType": "卖出",
        "nav_unit": 0.0,
        "nav_acc": 0.0,
        "volume": 0,
        "dealMoney": 10000.0,
        "fee": 0.0,
        "occurMoney": 10000.0,
        "account": "华泰证券",
        "category1": "无",
        "category2": "无",
        "category3": "无",
        "categoryId": 1,
        "note": "122扣除金额 基金代码：003474,发生份额：10000"
    },
    {
        "id": 46,
        "date": "2019-02-22",
        "code": "003474",
        "name": " ",
        "dealType": "卖出",
        "nav_unit": 0.0,
        "nav_acc": 0.0,
        "volume": 0,
        "dealMoney": 10000.0,
        "fee": 0.0,
        "occurMoney": 10000.0,
        "account": "华泰证券",
        "category1": "无",
        "category2": "无",
        "category3": "无",
        "categoryId": 1,
        "note": "124增加金额 基金代码：003474,发生份额：10000"
    },
    {
        "id": 47,
        "date": "2019-02-25",
        "code": "nan",
        "name": " ",
        "dealType": "卖出",
        "nav_unit": 0.0,
        "nav_acc": 0.0,
        "volume": 0,
        "dealMoney": 10000.0,
        "fee": 0.0,
        "occurMoney": 10000.0,
        "account": "华泰证券",
        "category1": "无",
        "category2": "无",
        "category3": "无",
        "categoryId": 1,
        "note": "银行返回码[ ]返回信息[0000 交易成功]|转账成功 转账账号:6225881012906292 correct_balance=10000"
    },
    {
        "id": 48,
        "date": "2019-03-08",
        "code": "nan",
        "name": " ",
        "dealType": "卖出",
        "nav_unit": 0.0,
        "nav_acc": 0.0,
        "volume": 0,
        "dealMoney": 8831.0,
        "fee": 0.0,
        "occurMoney": 8831.0,
        "account": "华泰证券",
        "category1": "无",
        "category2": "无",
        "category3": "无",
        "categoryId": 1,
        "note": "银行返回码[ ]返回信息[0000 交易成功]|转账成功 转账账号:6225881012906292 correct_balance=8831"
    },
    {
        "id": 49,
        "date": "2019-03-21",
        "code": "nan",
        "name": " ",
        "dealType": "卖出",
        "nav_unit": 0.0,
        "nav_acc": 0.0,
        "volume": 0,
        "dealMoney": 0.4,
        "fee": 0.0,
        "occurMoney": 0.4,
        "account": "华泰证券",
        "category1": "无",
        "category2": "无",
        "category3": "无",
        "categoryId": 1,
        "note": " 利息归本: 归本利息为 0.4correct_balance=0"
    },
    {
        "id": 50,
        "date": "2019-05-15",
        "code": "nan",
        "name": " ",
        "dealType": "卖出",
        "nav_unit": 0.0,
        "nav_acc": 0.0,
        "volume": 0,
        "dealMoney": 6500.0,
        "fee": 0.0,
        "occurMoney": 6500.0,
        "account": "华泰证券",
        "category1": "无",
        "category2": "无",
        "category3": "无",
        "categoryId": 1,
        "note": "银行返回码[ ]返回信息[0000 交易成功]|转账成功 转账账号:6225881012906292 correct_balance=0"
    },
    {
        "id": 51,
        "date": "2019-06-18",
        "code": "nan",
        "name": " ",
        "dealType": "卖出",
        "nav_unit": 0.0,
        "nav_acc": 0.0,
        "volume": 0,
        "dealMoney": 6400.0,
        "fee": 0.0,
        "occurMoney": 6400.0,
        "account": "华泰证券",
        "category1": "无",
        "category2": "无",
        "category3": "无",
        "categoryId": 1,
        "note": "银行返回码[ ]返回信息[0000 交易成功]|转账成功 转账账号:6225881012906292 correct_balance=0"
    },
    {
        "id": 52,
        "date": "2019-06-18",
        "code": "nan",
        "name": " ",
        "dealType": "卖出",
        "nav_unit": 0.0,
        "nav_acc": 0.0,
        "volume": 0,
        "dealMoney": 6400.0,
        "fee": 0.0,
        "occurMoney": 6400.0,
        "account": "华泰证券",
        "category1": "无",
        "category2": "无",
        "category3": "无",
        "categoryId": 1,
        "note": "银行返回码[ ]返回信息[0000 交易成功]|转账成功 转账账号:6225881012906292 correct_balance=0"
    },
    {
        "id": 53,
        "date": "2019-07-01",
        "code": "nan",
        "name": " ",
        "dealType": "卖出",
        "nav_unit": 0.0,
        "nav_acc": 0.0,
        "volume": 0,
        "dealMoney": 6100.0,
        "fee": 0.0,
        "occurMoney": 6100.0,
        "account": "华泰证券",
        "category1": "无",
        "category2": "无",
        "category3": "无",
        "categoryId": 1,
        "note": "银行返回码[ ]返回信息[0000 交易成功]|转账成功 转账账号:6225881012906292 correct_balance=0"
    },
    {
        "id": 54,
        "date": "2019-09-26",
        "code": "nan",
        "name": " ",
        "dealType": "卖出",
        "nav_unit": 0.0,
        "nav_acc": 0.0,
        "volume": 0,
        "dealMoney": 3500.0,
        "fee": 0.0,
        "occurMoney": 3500.0,
        "account": "华泰证券",
        "category1": "无",
        "category2": "无",
        "category3": "无",
        "categoryId": 1,
        "note": "银行返回码[ ]返回信息[0000 交易成功]|转账成功 转账账号:6225881012906292 correct_balance=0"
    },
    {
        "id": 55,
        "date": "2019-11-06",
        "code": "nan",
        "name": " ",
        "dealType": "卖出",
        "nav_unit": 0.0,
        "nav_acc": 0.0,
        "volume": 0,
        "dealMoney": 66.14,
        "fee": 0.0,
        "occurMoney": 66.14,
        "account": "华泰证券",
        "category1": "无",
        "category2": "无",
        "category3": "无",
        "categoryId": 1,
        "note": "银行返回码[ ]返回信息[0000 交易成功]|转账成功 转账账号:6225881012906292 correct_balance=66.14"
    },
    {
        "id": 56,
        "date": "2019-11-06",
        "code": "nan",
        "name": " ",
        "dealType": "卖出",
        "nav_unit": 0.0,
        "nav_acc": 0.0,
        "volume": 0,
        "dealMoney": 3727.0,
        "fee": 0.0,
        "occurMoney": 3727.0,
        "account": "华泰证券",
        "category1": "无",
        "category2": "无",
        "category3": "无",
        "categoryId": 1,
        "note": "银行返回码[ ]返回信息[0000 交易成功]|转账成功 转账账号:6225881012906292 correct_balance=3727"
    },
    {
        "id": 57,
        "date": "2019-11-11",
        "code": "nan",
        "name": " ",
        "dealType": "卖出",
        "nav_unit": 0.0,
        "nav_acc": 0.0,
        "volume": 0,
        "dealMoney": 3300.0,
        "fee": 0.0,
        "occurMoney": 3300.0,
        "account": "华泰证券",
        "category1": "无",
        "category2": "无",
        "category3": "无",
        "categoryId": 1,
        "note": "银行返回码[ ]返回信息[0000 交易成功]|转账成功 转账账号:6225881012906292 correct_balance=0"
    },
    {
        "id": 58,
        "date": "2019-11-20",
        "code": "nan",
        "name": " ",
        "dealType": "卖出",
        "nav_unit": 0.0,
        "nav_acc": 0.0,
        "volume": 0,
        "dealMoney": 32000.0,
        "fee": 0.0,
        "occurMoney": 32000.0,
        "account": "华泰证券",
        "category1": "无",
        "category2": "无",
        "category3": "无",
        "categoryId": 1,
        "note": "银行返回码[ ]返回信息[0000 交易成功]|转账成功 转账账号:6225881012906292 correct_balance=0"
    },
    {
        "id": 59,
        "date": "2019-11-21",
        "code": "nan",
        "name": " ",
        "dealType": "卖出",
        "nav_unit": 0.0,
        "nav_acc": 0.0,
        "volume": 0,
        "dealMoney": 32131.0,
        "fee": 0.0,
        "occurMoney": 32131.0,
        "account": "华泰证券",
        "category1": "无",
        "category2": "无",
        "category3": "无",
        "categoryId": 1,
        "note": "银行返回码[ ]返回信息[0000 交易成功]|转账成功 转账账号:6225881012906292 correct_balance=32131"
    },
    {
        "id": 60,
        "date": "2019-11-25",
        "code": "nan",
        "name": " ",
        "dealType": "卖出",
        "nav_unit": 0.0,
        "nav_acc": 0.0,
        "volume": 0,
        "dealMoney": 3600.0,
        "fee": 0.0,
        "occurMoney": 3600.0,
        "account": "华泰证券",
        "category1": "无",
        "category2": "无",
        "category3": "无",
        "categoryId": 1,
        "note": "银行返回码[ ]返回信息[0000 交易成功]|转账成功 转账账号:6225881012906292 correct_balance=0"
    },
    {
        "id": 61,
        "date": "2019-11-28",
        "code": "nan",
        "name": " ",
        "dealType": "卖出",
        "nav_unit": 0.0,
        "nav_acc": 0.0,
        "volume": 0,
        "dealMoney": 3569.51,
        "fee": 0.0,
        "occurMoney": 3569.51,
        "account": "华泰证券",
        "category1": "无",
        "category2": "无",
        "category3": "无",
        "categoryId": 1,
        "note": "银行返回码[ ]返回信息[0000 交易成功]|转账成功 转账账号:6225881012906292 correct_balance=3569.51"
    },
    {
        "id": 62,
        "date": "2019-12-05",
        "code": " ",
        "name": " ",
        "dealType": "卖出",
        "nav_unit": 0.0,
        "nav_acc": 0.0,
        "volume": 0,
        "dealMoney": 126.9,
        "fee": 0.0,
        "occurMoney": 126.9,
        "account": "华泰证券",
        "category1": "无",
        "category2": "无",
        "category3": "无",
        "categoryId": 1,
        "note": "122扣除金额 基金代码：940018,发生份额：126.9"
    },
    {
        "id": 63,
        "date": "2019-12-16",
        "code": " ",
        "name": " ",
        "dealType": "卖出",
        "nav_unit": 0.0,
        "nav_acc": 0.0,
        "volume": 0,
        "dealMoney": 564.2,
        "fee": 0.0,
        "occurMoney": 564.2,
        "account": "华泰证券",
        "category1": "无",
        "category2": "无",
        "category3": "无",
        "categoryId": 1,
        "note": "122扣除金额 基金代码：940018,发生份额：564.2"
    },
    {
        "id": 64,
        "date": "2019-12-18",
        "code": " ",
        "name": " ",
        "dealType": "卖出",
        "nav_unit": 0.0,
        "nav_acc": 0.0,
        "volume": 0,
        "dealMoney": 722.35,
        "fee": 0.0,
        "occurMoney": 722.35,
        "account": "华泰证券",
        "category1": "无",
        "category2": "无",
        "category3": "无",
        "categoryId": 1,
        "note": "124增加金额 基金代码：940018,发生份额：722.35"
    },
    {
        "id": 65,
        "date": "2019-12-19",
        "code": " ",
        "name": " ",
        "dealType": "卖出",
        "nav_unit": 0.0,
        "nav_acc": 0.0,
        "volume": 0,
        "dealMoney": 0.0,
        "fee": 0.0,
        "occurMoney": 0.0,
        "account": "华泰证券",
        "category1": "无",
        "category2": "无",
        "category3": "无",
        "categoryId": 1,
        "note": "银行返回码[ ]返回信息[0000 交易成功]|转账成功 转账账号:6225881012906292 correct_balance=722.35"
    },
    {
        "id": 66,
        "date": "2019-12-23",
        "code": " ",
        "name": " ",
        "dealType": "卖出",
        "nav_unit": 0.0,
        "nav_acc": 0.0,
        "volume": 0,
        "dealMoney": 0.13,
        "fee": 0.0,
        "occurMoney": 0.13,
        "account": "华泰证券",
        "category1": "无",
        "category2": "无",
        "category3": "无",
        "categoryId": 1,
        "note": " 利息归本: 归本利息为 0.13correct_balance=0"
    },
    {
        "id": 67,
        "date": "2019-12-24",
        "code": " ",
        "name": " ",
        "dealType": "卖出",
        "nav_unit": 0.0,
        "nav_acc": 0.0,
        "volume": 0,
        "dealMoney": 0.0,
        "fee": 0.0,
        "occurMoney": 0.0,
        "account": "华泰证券",
        "category1": "无",
        "category2": "无",
        "category3": "无",
        "categoryId": 1,
        "note": "122扣除金额 基金代码：940018,发生份额：.13"
    },
    {
        "id": 68,
        "date": "2020-02-26",
        "code": " ",
        "name": " ",
        "dealType": "卖出",
        "nav_unit": 0.0,
        "nav_acc": 0.0,
        "volume": 0,
        "dealMoney": -16662.07,
        "fee": 0.0,
        "occurMoney": -16662.07,
        "account": "华泰证券",
        "category1": "无",
        "category2": "无",
        "category3": "无",
        "categoryId": 1,
        "note": "122扣除金额 基金代码：940018,发生份额：16662.07"
    },
    {
        "id": 69,
        "date": "2020-02-27",
        "code": " ",
        "name": " ",
        "dealType": "卖出",
        "nav_unit": 0.0,
        "nav_acc": 0.0,
        "volume": 0,
        "dealMoney": 16662.0,
        "fee": 0.0,
        "occurMoney": 16662.0,
        "account": "华泰证券",
        "category1": "无",
        "category2": "无",
        "category3": "无",
        "categoryId": 1,
        "note": "快速取现退出资金拨入,产品代码940018,对方资产账户40000545correct_balance=0"
    },
    {
        "id": 70,
        "date": "2020-02-27",
        "code": " ",
        "name": " ",
        "dealType": "卖出",
        "nav_unit": 0.0,
        "nav_acc": 0.0,
        "volume": 0,
        "dealMoney": -16663.0,
        "fee": 0.0,
        "occurMoney": -16663.0,
        "account": "华泰证券",
        "category1": "无",
        "category2": "无",
        "category3": "无",
        "categoryId": 1,
        "note": "银行返回码[ ]返回信息[0000 交易成功]|转账成功 转账账号:6225881012906292 correct_balance=16663"
    },
    {
        "id": 71,
        "date": "2020-03-10",
        "code": " ",
        "name": " ",
        "dealType": "卖出",
        "nav_unit": 0.0,
        "nav_acc": 0.0,
        "volume": 0,
        "dealMoney": -9885.02,
        "fee": 0.0,
        "occurMoney": -9885.02,
        "account": "华泰证券",
        "category1": "无",
        "category2": "无",
        "category3": "无",
        "categoryId": 1,
        "note": "122扣除金额 基金代码：940018,发生份额：9885.02"
    },
    {
        "id": 72,
        "date": "2020-03-11",
        "code": " ",
        "name": " ",
        "dealType": "卖出",
        "nav_unit": 0.0,
        "nav_acc": 0.0,
        "volume": 0,
        "dealMoney": 9885.0,
        "fee": 0.0,
        "occurMoney": 9885.0,
        "account": "华泰证券",
        "category1": "无",
        "category2": "无",
        "category3": "无",
        "categoryId": 1,
        "note": "快速取现退出资金拨入,产品代码940018,对方资产账户40000545correct_balance=0"
    },
    {
        "id": 73,
        "date": "2020-03-11",
        "code": " ",
        "name": " ",
        "dealType": "卖出",
        "nav_unit": 0.0,
        "nav_acc": 0.0,
        "volume": 0,
        "dealMoney": -9886.0,
        "fee": 0.0,
        "occurMoney": -9886.0,
        "account": "华泰证券",
        "category1": "无",
        "category2": "无",
        "category3": "无",
        "categoryId": 1,
        "note": "银行返回码[ ]返回信息[0000 交易成功]|转账成功 转账账号:6225881012906292 correct_balance=9886"
    },
    {
        "id": 74,
        "date": "2020-03-11",
        "code": " ",
        "name": " ",
        "dealType": "卖出",
        "nav_unit": 0.0,
        "nav_acc": 0.0,
        "volume": 0,
        "dealMoney": 0.46,
        "fee": 0.0,
        "occurMoney": 0.46,
        "account": "华泰证券",
        "category1": "无",
        "category2": "无",
        "category3": "无",
        "categoryId": 1,
        "note": "124增加金额 基金代码：940018,发生份额：.46"
    },
    {
        "id": 75,
        "date": "2020-03-13",
        "code": " ",
        "name": " ",
        "dealType": "卖出",
        "nav_unit": 0.0,
        "nav_acc": 0.0,
        "volume": 0,
        "dealMoney": -7634.13,
        "fee": 0.0,
        "occurMoney": -7634.13,
        "account": "华泰证券",
        "category1": "无",
        "category2": "无",
        "category3": "无",
        "categoryId": 1,
        "note": "122扣除金额 基金代码：940018,发生份额：7634.13"
    },
    {
        "id": 76,
        "date": "2020-03-16",
        "code": " ",
        "name": " ",
        "dealType": "卖出",
        "nav_unit": 0.0,
        "nav_acc": 0.0,
        "volume": 0,
        "dealMoney": 7634.0,
        "fee": 0.0,
        "occurMoney": 7634.0,
        "account": "华泰证券",
        "category1": "无",
        "category2": "无",
        "category3": "无",
        "categoryId": 1,
        "note": "快速取现退出资金拨入,产品代码940018,对方资产账户40000545correct_balance=0"
    },
    {
        "id": 77,
        "date": "2020-03-16",
        "code": " ",
        "name": " ",
        "dealType": "卖出",
        "nav_unit": 0.0,
        "nav_acc": 0.0,
        "volume": 0,
        "dealMoney": -7635.0,
        "fee": 0.0,
        "occurMoney": -7635.0,
        "account": "华泰证券",
        "category1": "无",
        "category2": "无",
        "category3": "无",
        "categoryId": 1,
        "note": "银行返回码[ ]返回信息[0000 交易成功]|转账成功 转账账号:6225881012906292 correct_balance=7635"
    },
    {
        "id": 78,
        "date": "2020-03-25",
        "code": " ",
        "name": " ",
        "dealType": "卖出",
        "nav_unit": 0.0,
        "nav_acc": 0.0,
        "volume": 0,
        "dealMoney": -7091.98,
        "fee": 0.0,
        "occurMoney": -7091.98,
        "account": "华泰证券",
        "category1": "无",
        "category2": "无",
        "category3": "无",
        "categoryId": 1,
        "note": "122扣除金额 基金代码：940018,发生份额：7091.98"
    },
    {
        "id": 79,
        "date": "2020-03-26",
        "code": " ",
        "name": " ",
        "dealType": "卖出",
        "nav_unit": 0.0,
        "nav_acc": 0.0,
        "volume": 0,
        "dealMoney": -1.0,
        "fee": 0.0,
        "occurMoney": -1.0,
        "account": "华泰证券",
        "category1": "无",
        "category2": "无",
        "category3": "无",
        "categoryId": 1,
        "note": "122扣除金额 基金代码：940018,发生份额：1"
    },
    {
        "id": 80,
        "date": "2020-04-28",
        "code": " ",
        "name": " ",
        "dealType": "卖出",
        "nav_unit": 0.0,
        "nav_acc": 0.0,
        "volume": 0,
        "dealMoney": 7093.0,
        "fee": 0.0,
        "occurMoney": 7093.0,
        "account": "华泰证券",
        "category1": "无",
        "category2": "无",
        "category3": "无",
        "categoryId": 1,
        "note": "快速取现退出资金拨入,产品代码940018,对方资产账户40000545correct_balance=0"
    },
    {
        "id": 81,
        "date": "2020-04-28",
        "code": " ",
        "name": " ",
        "dealType": "卖出",
        "nav_unit": 0.0,
        "nav_acc": 0.0,
        "volume": 0,
        "dealMoney": -7093.0,
        "fee": 0.0,
        "occurMoney": -7093.0,
        "account": "华泰证券",
        "category1": "无",
        "category2": "无",
        "category3": "无",
        "categoryId": 1,
        "note": "银行返回码[ ]返回信息[0000 交易成功]|转账成功 转账账号:6225881012906292 correct_balance=7093"
    },
    {
        "id": 82,
        "date": "2020-04-28",
        "code": " ",
        "name": " ",
        "dealType": "卖出",
        "nav_unit": 0.0,
        "nav_acc": 0.0,
        "volume": 0,
        "dealMoney": -25387.13,
        "fee": 0.0,
        "occurMoney": -25387.13,
        "account": "华泰证券",
        "category1": "无",
        "category2": "无",
        "category3": "无",
        "categoryId": 1,
        "note": "122扣除金额 基金代码：940018,发生份额：25387.13"
    },
    {
        "id": 83,
        "date": "2020-04-29",
        "code": " ",
        "name": " ",
        "dealType": "卖出",
        "nav_unit": 0.0,
        "nav_acc": 0.0,
        "volume": 0,
        "dealMoney": 25397.0,
        "fee": 0.0,
        "occurMoney": 25397.0,
        "account": "华泰证券",
        "category1": "无",
        "category2": "无",
        "category3": "无",
        "categoryId": 1,
        "note": "快速取现退出资金拨入,产品代码940018,对方资产账户40000545correct_balance=0"
    },
    {
        "id": 84,
        "date": "2020-04-29",
        "code": " ",
        "name": " ",
        "dealType": "卖出",
        "nav_unit": 0.0,
        "nav_acc": 0.0,
        "volume": 0,
        "dealMoney": -25398.0,
        "fee": 0.0,
        "occurMoney": -25398.0,
        "account": "华泰证券",
        "category1": "无",
        "category2": "无",
        "category3": "无",
        "categoryId": 1,
        "note": "银行返回码[ ]返回信息[0000 交易成功]|转账成功 转账账号:6225881012906292 correct_balance=25398"
    },
    {
        "id": 85,
        "date": "2020-04-29",
        "code": " ",
        "name": " ",
        "dealType": "卖出",
        "nav_unit": 0.0,
        "nav_acc": 0.0,
        "volume": 0,
        "dealMoney": 0.35,
        "fee": 0.0,
        "occurMoney": 0.35,
        "account": "华泰证券",
        "category1": "无",
        "category2": "无",
        "category3": "无",
        "categoryId": 1,
        "note": "124增加金额 基金代码：940018,发生份额：.35"
    },
    {
        "id": 86,
        "date": "2020-04-30",
        "code": " ",
        "name": " ",
        "dealType": "卖出",
        "nav_unit": 0.0,
        "nav_acc": 0.0,
        "volume": 0,
        "dealMoney": -63210.75,
        "fee": 0.0,
        "occurMoney": -63210.75,
        "account": "华泰证券",
        "category1": "无",
        "category2": "无",
        "category3": "无",
        "categoryId": 1,
        "note": "122扣除金额 基金代码：940018,发生份额：63210.75"
    },
    {
        "id": 87,
        "date": "2020-05-06",
        "code": " ",
        "name": " ",
        "dealType": "卖出",
        "nav_unit": 0.0,
        "nav_acc": 0.0,
        "volume": 0,
        "dealMoney": 63210.0,
        "fee": 0.0,
        "occurMoney": 63210.0,
        "account": "华泰证券",
        "category1": "无",
        "category2": "无",
        "category3": "无",
        "categoryId": 1,
        "note": "快速取现退出资金拨入,产品代码940018,对方资产账户40000545correct_balance=0"
    },
    {
        "id": 88,
        "date": "2020-05-06",
        "code": " ",
        "name": " ",
        "dealType": "卖出",
        "nav_unit": 0.0,
        "nav_acc": 0.0,
        "volume": 0,
        "dealMoney": -63211.35,
        "fee": 0.0,
        "occurMoney": -63211.35,
        "account": "华泰证券",
        "category1": "无",
        "category2": "无",
        "category3": "无",
        "categoryId": 1,
        "note": "银行返回码[ ]返回信息[0000 交易成功]|转账成功 转账账号:6225881012906292 correct_balance=63211.35"
    },
    {
        "id": 89,
        "date": "2020-05-06",
        "code": " ",
        "name": " ",
        "dealType": "卖出",
        "nav_unit": 0.0,
        "nav_acc": 0.0,
        "volume": 0,
        "dealMoney": 0.75,
        "fee": 0.0,
        "occurMoney": 0.75,
        "account": "华泰证券",
        "category1": "无",
        "category2": "无",
        "category3": "无",
        "categoryId": 1,
        "note": "124增加金额 基金代码：940018,发生份额：.75"
    },
    {
        "id": 90,
        "date": "2020-05-08",
        "code": " ",
        "name": " ",
        "dealType": "卖出",
        "nav_unit": 0.0,
        "nav_acc": 0.0,
        "volume": 0,
        "dealMoney": -0.75,
        "fee": 0.0,
        "occurMoney": -0.75,
        "account": "华泰证券",
        "category1": "无",
        "category2": "无",
        "category3": "无",
        "categoryId": 1,
        "note": "122扣除金额 基金代码：940018,发生份额：.75"
    },
    {
        "id": 91,
        "date": "2020-05-11",
        "code": " ",
        "name": " ",
        "dealType": "卖出",
        "nav_unit": 0.0,
        "nav_acc": 0.0,
        "volume": 0,
        "dealMoney": 0.39,
        "fee": 0.0,
        "occurMoney": 0.39,
        "account": "华泰证券",
        "category1": "无",
        "category2": "无",
        "category3": "无",
        "categoryId": 1,
        "note": "124增加金额 基金代码：004749,发生份额：.39"
    },
    {
        "id": 92,
        "date": "2020-05-12",
        "code": " ",
        "name": " ",
        "dealType": "卖出",
        "nav_unit": 0.0,
        "nav_acc": 0.0,
        "volume": 0,
        "dealMoney": 1.8,
        "fee": 0.0,
        "occurMoney": 1.8,
        "account": "华泰证券",
        "category1": "无",
        "category2": "无",
        "category3": "无",
        "categoryId": 1,
        "note": "124增加金额 基金代码：003474,发生份额：1.8,基金实时交收入账"
    },
    {
        "id": 93,
        "date": "2020-05-12",
        "code": " ",
        "name": " ",
        "dealType": "卖出",
        "nav_unit": 0.0,
        "nav_acc": 0.0,
        "volume": 0,
        "dealMoney": -2.19,
        "fee": 0.0,
        "occurMoney": -2.19,
        "account": "华泰证券",
        "category1": "无",
        "category2": "无",
        "category3": "无",
        "categoryId": 1,
        "note": "122扣除金额 基金代码：940018,发生份额：2.19"
    },
    {
        "id": 94,
        "date": "2020-05-19",
        "code": " ",
        "name": " ",
        "dealType": "卖出",
        "nav_unit": 0.0,
        "nav_acc": 0.0,
        "volume": 0,
        "dealMoney": -10786.04,
        "fee": 0.0,
        "occurMoney": -10786.04,
        "account": "华泰证券",
        "category1": "无",
        "category2": "无",
        "category3": "无",
        "categoryId": 1,
        "note": "122扣除金额 基金代码：940018,发生份额：10786.04"
    },
    {
        "id": 95,
        "date": "2020-05-20",
        "code": " ",
        "name": " ",
        "dealType": "卖出",
        "nav_unit": 0.0,
        "nav_acc": 0.0,
        "volume": 0,
        "dealMoney": -1.0,
        "fee": 0.0,
        "occurMoney": -1.0,
        "account": "华泰证券",
        "category1": "无",
        "category2": "无",
        "category3": "无",
        "categoryId": 1,
        "note": "122扣除金额 基金代码：940018,发生份额：1"
    },
    {
        "id": 96,
        "date": "2020-05-22",
        "code": " ",
        "name": " ",
        "dealType": "卖出",
        "nav_unit": 0.0,
        "nav_acc": 0.0,
        "volume": 0,
        "dealMoney": 10789.0,
        "fee": 0.0,
        "occurMoney": 10789.0,
        "account": "华泰证券",
        "category1": "无",
        "category2": "无",
        "category3": "无",
        "categoryId": 1,
        "note": "快速取现退出资金拨入,产品代码940018,对方资产账户40000545correct_balance=0"
    },
    {
        "id": 97,
        "date": "2020-05-22",
        "code": " ",
        "name": " ",
        "dealType": "卖出",
        "nav_unit": 0.0,
        "nav_acc": 0.0,
        "volume": 0,
        "dealMoney": -10789.0,
        "fee": 0.0,
        "occurMoney": -10789.0,
        "account": "华泰证券",
        "category1": "无",
        "category2": "无",
        "category3": "无",
        "categoryId": 1,
        "note": "银行返回码[ ]返回信息[0000 交易成功]|转账成功 转账账号:6225881012906292 correct_balance=10789"
    },
    {
        "id": 98,
        "date": "2020-05-26",
        "code": " ",
        "name": " ",
        "dealType": "卖出",
        "nav_unit": 0.0,
        "nav_acc": 0.0,
        "volume": 0,
        "dealMoney": -10570.09,
        "fee": 0.0,
        "occurMoney": -10570.09,
        "account": "华泰证券",
        "category1": "无",
        "category2": "无",
        "category3": "无",
        "categoryId": 1,
        "note": "122扣除金额 基金代码：940018,发生份额：10570.09"
    },
    {
        "id": 99,
        "date": "2020-05-27",
        "code": " ",
        "name": " ",
        "dealType": "卖出",
        "nav_unit": 0.0,
        "nav_acc": 0.0,
        "volume": 0,
        "dealMoney": 10571.0,
        "fee": 0.0,
        "occurMoney": 10571.0,
        "account": "华泰证券",
        "category1": "无",
        "category2": "无",
        "category3": "无",
        "categoryId": 1,
        "note": "快速取现退出资金拨入,产品代码940018,对方资产账户40000545correct_balance=0"
    },
    {
        "id": 100,
        "date": "2020-05-27",
        "code": " ",
        "name": " ",
        "dealType": "卖出",
        "nav_unit": 0.0,
        "nav_acc": 0.0,
        "volume": 0,
        "dealMoney": -10572.0,
        "fee": 0.0,
        "occurMoney": -10572.0,
        "account": "华泰证券",
        "category1": "无",
        "category2": "无",
        "category3": "无",
        "categoryId": 1,
        "note": "银行返回码[ ]返回信息[0000 交易成功]|转账成功 转账账号:6225881012906292 correct_balance=10572"
    },
    {
        "id": 101,
        "date": "2020-05-27",
        "code": " ",
        "name": " ",
        "dealType": "卖出",
        "nav_unit": 0.0,
        "nav_acc": 0.0,
        "volume": 0,
        "dealMoney": 0.93,
        "fee": 0.0,
        "occurMoney": 0.93,
        "account": "华泰证券",
        "category1": "无",
        "category2": "无",
        "category3": "无",
        "categoryId": 1,
        "note": "124增加金额 基金代码：940018,发生份额：.93"
    },
    {
        "id": 102,
        "date": "2020-05-29",
        "code": " ",
        "name": " ",
        "dealType": "卖出",
        "nav_unit": 0.0,
        "nav_acc": 0.0,
        "volume": 0,
        "dealMoney": -10549.42,
        "fee": 0.0,
        "occurMoney": -10549.42,
        "account": "华泰证券",
        "category1": "无",
        "category2": "无",
        "category3": "无",
        "categoryId": 1,
        "note": "122扣除金额 基金代码：940018,发生份额：10549.42"
    },
    {
        "id": 103,
        "date": "2020-06-01",
        "code": " ",
        "name": " ",
        "dealType": "卖出",
        "nav_unit": 0.0,
        "nav_acc": 0.0,
        "volume": 0,
        "dealMoney": -10797.84,
        "fee": 0.0,
        "occurMoney": -10797.84,
        "account": "华泰证券",
        "category1": "无",
        "category2": "无",
        "category3": "无",
        "categoryId": 1,
        "note": "122扣除金额 基金代码：940018,发生份额：10797.84"
    },
    {
        "id": 104,
        "date": "2020-06-02",
        "code": " ",
        "name": " ",
        "dealType": "卖出",
        "nav_unit": 0.0,
        "nav_acc": 0.0,
        "volume": 0,
        "dealMoney": 19891.0,
        "fee": 0.0,
        "occurMoney": 19891.0,
        "account": "华泰证券",
        "category1": "无",
        "category2": "无",
        "category3": "无",
        "categoryId": 1,
        "note": "快速取现退出资金拨入,产品代码940018,对方资产账户40000545correct_balance=0"
    },
    {
        "id": 105,
        "date": "2020-06-02",
        "code": " ",
        "name": " ",
        "dealType": "卖出",
        "nav_unit": 0.0,
        "nav_acc": 0.0,
        "volume": 0,
        "dealMoney": -19892.0,
        "fee": 0.0,
        "occurMoney": -19892.0,
        "account": "华泰证券",
        "category1": "无",
        "category2": "无",
        "category3": "无",
        "categoryId": 1,
        "note": "银行返回码[ ]返回信息[0000 交易成功]|转账成功 转账账号:6225881012906292 correct_balance=19892"
    },
    {
        "id": 106,
        "date": "2020-06-02",
        "code": " ",
        "name": " ",
        "dealType": "卖出",
        "nav_unit": 0.0,
        "nav_acc": 0.0,
        "volume": 0,
        "dealMoney": 1456.0,
        "fee": 0.0,
        "occurMoney": 1456.0,
        "account": "华泰证券",
        "category1": "无",
        "category2": "无",
        "category3": "无",
        "categoryId": 1,
        "note": "快速取现退出资金拨入,产品代码940018,对方资产账户40000545correct_balance=0"
    },
    {
        "id": 107,
        "date": "2020-06-02",
        "code": " ",
        "name": " ",
        "dealType": "卖出",
        "nav_unit": 0.0,
        "nav_acc": 0.0,
        "volume": 0,
        "dealMoney": -1456.0,
        "fee": 0.0,
        "occurMoney": -1456.0,
        "account": "华泰证券",
        "category1": "无",
        "category2": "无",
        "category3": "无",
        "categoryId": 1,
        "note": "银行返回码[ ]返回信息[0000 交易成功]|转账成功 转账账号:6225881012906292 correct_balance=1456"
    }
]